verilator/counter.v
module counter #(
  parameter WIDTH = 8
)(
  // system signals
  input  wire             clk,
  input  wire             rst,
  // counter signas
  input  wire             cen,  // counter enable
  input  wire             wen,  // write enable
  input  wire [WIDTH-1:0] dat,  // input data
  output reg  [WIDTH-1:0] o_p,  // output value (posedge counter)
  output reg  [WIDTH-1:0] o_n   // output value (negedge counter)
);


always @ (posedge clk, posedge rst)
if (rst) o_p <= {WIDTH{1'b0}};
else     o_p <= wen ? dat : o_p + {{WIDTH-1{1'b0}}, cen};


always @ (negedge clk, posedge rst)
if (rst) o_n <= {WIDTH{1'b0}};
else     o_n <= wen ? dat : o_n + {{WIDTH-1{1'b0}}, cen};

reg [31:0] clks;

initial begin
   clks = 0;
end

always @(posedge clk) begin
   clks <= clks + 1;
end

always @(posedge clk) begin
   $display("@%d ----- xxx -----", clks);
end

logic [1:0] sel;
logic [3:0] data;

assign sel = clks[1:0];

assign data = sel == 0 ? 4'd0 :
              sel == 1 ? 4'd1 :
              sel == 2 ? 4'd2 :
              sel == 3 ? 4'd3 :
              sel == 4 ? 4'd4 :
              sel == 5 ? 4'd5 :
              sel == 6 ? 4'd6 :
              sel == 7 ? 4'd7 :
              sel == 8 ? 4'd8 :
              sel == 9 ? 4'd9 :
                         4'd0 ;

always @(negedge clk) begin
   $display("    sel %2d --> data %4d", sel, data);
end

endmodule

verilator/counter.vcd
$version Generated by VerilatedVcd $end
$date Tue Jul 23 21:48:06 2019
 $end
$timescale   1ns $end

 $scope module TOP $end
  $var wire  1 ( cen $end
  $var wire  1 & clk $end
  $var wire  8 * dat [7:0] $end
  $var wire  8 , o_n [7:0] $end
  $var wire  8 + o_p [7:0] $end
  $var wire  1 ' rst $end
  $var wire  1 ) wen $end
  $scope module counter $end
   $var wire 32 - WIDTH [31:0] $end
   $var wire  1 ( cen $end
   $var wire  1 & clk $end
   $var wire 32 # clks [31:0] $end
   $var wire  8 * dat [7:0] $end
   $var wire  4 % data [3:0] $end
   $var wire  8 , o_n [7:0] $end
   $var wire  8 + o_p [7:0] $end
   $var wire  1 ' rst $end
   $var wire  2 $ sel [1:0] $end
   $var wire  1 ) wen $end
  $upscope $end
 $upscope $end
$enddefinitions $end


#0
b00000000000000000000000000000000 #
b00 $
b0000 %
1&
1'
0(
0)
b01010101 *
b00000000 +
b00000000 ,
b00000000000000000000000000001000 -
#1
0&
#2
b00000000000000000000000000000001 #
b01 $
b0001 %
1&
#3
0&
#4
b00000000000000000000000000000010 #
b10 $
b0010 %
1&
0'
#5
0&
#6
b00000000000000000000000000000011 #
b11 $
b0011 %
1&
#7
0&
#8
b00000000000000000000000000000100 #
b00 $
b0000 %
1&
#9
0&
#10
b00000000000000000000000000000101 #
b01 $
b0001 %
1&
#11
0&
#12
b00000000000000000000000000000110 #
b10 $
b0010 %
1&
#13
0&
#14
b00000000000000000000000000000111 #
b11 $
b0011 %
1&
1(
#15
0&
b00000001 ,
#16
b00000000000000000000000000001000 #
b00 $
b0000 %
1&
b00000001 +
#17
0&
b00000010 ,
#18
b00000000000000000000000000001001 #
b01 $
b0001 %
1&
b00000010 +
#19
0&
b00000011 ,
#20
b00000000000000000000000000001010 #
b10 $
b0010 %
1&
b00000011 +
#21
0&
b00000100 ,
#22
b00000000000000000000000000001011 #
b11 $
b0011 %
1&
1)
b00000100 +
#23
0&
b01010101 ,
#24
b00000000000000000000000000001100 #
b00 $
b0000 %
1&
0)
b01010101 +
#25
0&
b01010110 ,
#26
b00000000000000000000000000001101 #
b01 $
b0001 %
1&
b01010110 +
#27
0&
b01010111 ,
#28
b00000000000000000000000000001110 #
b10 $
b0010 %
1&
b01010111 +
#29
0&
b01011000 ,
#30
b00000000000000000000000000001111 #
b11 $
b0011 %
1&
b01011000 +
#31
0&
b01011001 ,
#32
b00000000000000000000000000010000 #
b00 $
b0000 %
1&
b01011001 +
#33
0&
b01011010 ,
#34
b00000000000000000000000000010001 #
b01 $
b0001 %
1&
b01011010 +
#35
0&
b01011011 ,
#36
b00000000000000000000000000010010 #
b10 $
b0010 %
1&
b01011011 +
#37
0&
b01011100 ,
#38
b00000000000000000000000000010011 #
b11 $
b0011 %
1&
b01011100 +
#39
0&
b01011101 ,
